LICENSE
setup.py
steer_llm.py
SteerLLM.egg-info/PKG-INFO
SteerLLM.egg-info/SOURCES.txt
SteerLLM.egg-info/dependency_links.txt
SteerLLM.egg-info/requires.txt
SteerLLM.egg-info/top_level.txt